bert_token_tagger/__init__.py
bert_token_tagger/utils.py
bert_token_tagger-0.2.0.dist-info/WHEEL
bert_token_tagger-0.2.0.dist-info/METADATA
bert_token_tagger-0.2.0.dist-info/RECORD
